s3/__init__.py
s3/__main__.py
s3/interpreter.py
s3interpreter-0.0.1.dist-info/licenses/LICENSE
s3interpreter-0.0.1.dist-info/METADATA
s3interpreter-0.0.1.dist-info/WHEEL
s3interpreter-0.0.1.dist-info/entry_points.txt
s3interpreter-0.0.1.dist-info/top_level.txt
s3interpreter-0.0.1.dist-info/RECORD
