Metadata-Version: 2.4
Name: s3interpreter
Version: 0.0.1
Summary: A simple interpreter for the S3 language.
Author: Zhvan
Classifier: Programming Language :: Python :: 3
Classifier: License :: OSI Approved :: MIT License
Classifier: Operating System :: OS Independent
Classifier: Development Status :: 3 - Alpha
Requires-Python: >=3.7
License-File: LICENSE
Dynamic: license-file
